covid19cases/__init__.py
covid19cases/covid19cases.py
COVID_19_Cases-0.0.3.dist-info/LICENSE
COVID_19_Cases-0.0.3.dist-info/METADATA
COVID_19_Cases-0.0.3.dist-info/WHEEL
COVID_19_Cases-0.0.3.dist-info/top_level.txt
COVID_19_Cases-0.0.3.dist-info/RECORD
